n8n_cli/__init__.py
n8n_cli/__main__.py
n8n_cli/cli.py
n8n_cli/completion.py
n8n_cli/config.py
n8n_cli/utils.py
n8n_cli/client/__init__.py
n8n_cli/client/core.py
n8n_cli/client/exceptions.py
n8n_cli/client/models/__init__.py
n8n_cli/client/models/execution.py
n8n_cli/client/models/project.py
n8n_cli/client/models/user.py
n8n_cli/client/models/workflow.py
n8n_cli/client/resources/__init__.py
n8n_cli/client/resources/executions.py
n8n_cli/client/resources/projects.py
n8n_cli/client/resources/users.py
n8n_cli/client/resources/workflows.py
n8n_cli/commands/__init__.py
n8n_cli/commands/execution.py
n8n_cli/commands/member.py
n8n_cli/commands/project.py
n8n_cli/commands/user.py
n8n_cli/commands/workflow.py
n8nctl-0.1.1.dist-info/METADATA
n8nctl-0.1.1.dist-info/WHEEL
n8nctl-0.1.1.dist-info/entry_points.txt
n8nctl-0.1.1.dist-info/licenses/LICENSE
n8nctl-0.1.1.dist-info/RECORD
