Metadata-Version: 2.4
Name: n8nctl
Version: 0.1.1
Summary: CLI for managing n8n Cloud workflows
Project-URL: Homepage, https://github.com/dbachelder/n8n-cli
Project-URL: Repository, https://github.com/dbachelder/n8n-cli
Project-URL: Issues, https://github.com/dbachelder/n8n-cli/issues
Author-email: Dan Bachelder <dan@codesushi.com>
License: MIT
License-File: LICENSE
Keywords: automation,cli,n8n,n8n-cloud,workflow
Classifier: Development Status :: 4 - Beta
Classifier: Intended Audience :: Developers
Classifier: License :: OSI Approved :: MIT License
Classifier: Programming Language :: Python :: 3
Classifier: Programming Language :: Python :: 3.12
Classifier: Topic :: Software Development :: Libraries :: Python Modules
Requires-Python: >=3.12
Requires-Dist: httpx>=0.27.0
Requires-Dist: pydantic-settings>=2.0
Requires-Dist: pydantic>=2.0
Requires-Dist: python-dotenv>=1.0
Requires-Dist: tenacity>=9.0
Requires-Dist: typer>=0.13.0
